agentic_workflow/__init__.py
agentic_workflow/adk/__init__.py
agentic_workflow/adk/auth/oauth_service.py
agentic_workflow/adk/models/app.py
agentic_workflow/adk/models/app_definition.py
agentic_workflow/adk/models/connection.py
agentic_workflow/adk/models/context.py
agentic_workflow/adk/models/executors.py
agentic_workflow/adk/models/workflow.py
agentic_workflow/adk/registry/app_registry.py
agentic_workflow/api/__init__.py
agentic_workflow/api/routes/__init__.py
agentic_workflow/api/routes/app.py
agentic_workflow/api/routes/connection.py
agentic_workflow/api/routes/workflow.py
agentic_workflow/apps/.gitkeep
agentic_workflow/apps/core/v1/actions/branch_action.py
agentic_workflow/apps/core/v1/actions/http_action.py
agentic_workflow/apps/core/v1/definition.py
agentic_workflow/apps/core/v1/triggers/webhook.py
agentic_workflow/apps/gmail/v1/actions/create_draft_action.py
agentic_workflow/apps/gmail/v1/actions/send_email_action.py
agentic_workflow/apps/gmail/v1/definition.py
agentic_workflow/apps/slack/v1/actions/send_channel_message_action.py
agentic_workflow/apps/slack/v1/actions/send_dm_action.py
agentic_workflow/apps/slack/v1/definition.py
agentic_workflow/apps/trata/v1/actions/get_contact_action.py
agentic_workflow/apps/trata/v1/actions/get_conversation_action.py
agentic_workflow/apps/trata/v1/actions/make_call_action.py
agentic_workflow/apps/trata/v1/definition.py
agentic_workflow/apps/trata/v1/triggers/attend_call_trigger.py
agentic_workflow/cli/sync_apps.py
agentic_workflow/constants.py
agentic_workflow/crud/app.py
agentic_workflow/crud/app_action.py
agentic_workflow/crud/base.py
agentic_workflow/crud/connection.py
agentic_workflow/crud/workflow.py
agentic_workflow/db/models.py
agentic_workflow/db/session.py
agentic_workflow/db/utils.py
agentic_workflow/main.py
agentic_workflow/migrations.py
agentic_workflow/models/base.py
agentic_workflow/utils/__init__.py
agentic_workflow/utils/auth.py
agentic_workflow/utils/helpers.py
agentic_workflow/utils/logger.py
agentic_workflow-0.0.8.dist-info/METADATA
agentic_workflow-0.0.8.dist-info/WHEEL
agentic_workflow-0.0.8.dist-info/entry_points.txt
agentic_workflow-0.0.8.dist-info/RECORD
